addition_modules.v
/*
Group 11 Lab 5 part 4

*/

//Compute 2's complimet of input
module twos_compliment(IN,OUT);
    
    input [7:0] IN;  // Input signal
    output [7:0] OUT;  // Two's complement output

    // Calculate two's complement
    assign #1 OUT = ~IN + 8'd1;

endmodule

//8 bit input 2x1 mux
module mux_2x1(IN0,IN1,SELECT,OUT);
    
    input [7:0] IN0,IN1;  // Input signals
    input SELECT;  // Selection signal
    output reg [7:0] OUT;  // Selected output

    always @(IN0,IN1,SELECT) begin
        // Select the input based on SELECT
        if (SELECT == 1'b0)
            OUT = IN0;
        else
            OUT = IN1;
    end
endmodule

//32 bit input 2x1 mux
module mux_32(IN0,IN1,SELECT,OUT);
    
    input [31:0] IN0,IN1;  // Input signals
    input SELECT;  // Selection signal
    output reg [31:0] OUT;  // Selected output

    always @(IN0,IN1,SELECT) begin
        // Select the input based on SELECT
        if (SELECT == 1'b0)
            OUT = IN0;
        else
            OUT = IN1;
    end
endmodule


//Extend address to 32 bit and leftshift by two for word alling 
module extend(address,byteAddress);
    
    input [7:0] address;
    output [31:0] byteAddress;

    assign byteAddress = { {32{address[7]}}, address,2'b00 };

endmodule

//Combinational AND for Branch Select signal. zero from ALU and branch from CU
module branchSel(branch,zero,branch_sel);
    input  branch,zero;
    output branch_sel;

    assign branch_sel=branch & zero;  //If zero=1 and branch =1, branch_sel=1 

endmodule

//Get Jump Address by concatenating most significant 4 bits of PC+4 with joffset
module concatenate(pc_4,joffset,jumpAddress);
    input [31:0] pc_4;  //PC+4
    input [7:0] joffset; //joffset from INSTRUCTION
    output [31:0] jumpAddress;  //32 bit jump adddress

    wire [27:0] extend_jump;

    assign extend_jump = {{26{joffset[7]}},joffset,2'b00};  //Extend 7 bit joffset and leftshift by 2
    assign jumpAddress = {pc_4[31:28],extend_jump};     //Concatenate [31:28] bits of PC+4 with [27:0] bits of extend_jump
endmodule

//Adder for PC+4
module pc_adder1(CURRENT_PC,PC_4);
   
    input [31:0] CURRENT_PC;  // Current program counter
    output [31:0] PC_4;  // Program counter + 4 output

    // Add 4 to the current program counter
    assign #1 PC_4 = CURRENT_PC + 32'd4;

endmodule

//Adder for ADD offset for PC
module pc_adder2(pc_4,offset,offset_pc);
   
    input [31:0] offset,pc_4;  // Current program counter
    output [31:0] offset_pc;  // Program counter + offset

    // Add offset to the current program counter
    assign #1 offset_pc = pc_4 + offset;

endmodule


//Program Counter
module pc_unit(CLK,RESET,NEXT_PC,PC);
    
    input CLK,RESET;  // Clock and reset signals
    input  [31:0] NEXT_PC;
    output reg [31:0] PC;  // Program counter output

    always @(posedge CLK) begin
        // Reset PC to 0 on reset signal
        if (RESET == 1'b1)
            #1 PC = 32'b0;
        else
            #1 PC = NEXT_PC;  // Update PC
    end
endmodule

alu.v
// Define the ALU module with inputs aluResult, select, data1, and data2
module alu(aluResult, select, data1, data2,zero);
    input [2:0] select;  // Input for selecting the ALU operation
    input [7:0] data1, data2;  // Input data for the ALU operations
    
    output reg [7:0] aluResult;  // Output result from the ALU
    output  zero;

    // Define internal wires for outputs from each unit
    wire [7:0] forwardOut, andOut, addOut, orOut;
    
    // Instantiate modules for ADD, AND, OR, and FORWARD units
    ADD add1(addOut, data1, data2,zero);
    AND and1(andOut, data1, data2);
    OR or1(orOut, data1, data2);
    FORWARD f(forwardOut, data2);

    // Always block to perform ALU operation based on select input and outputs from units
    always @ (forwardOut, addOut, andOut, orOut, select) begin
        case (select)
            3'b000 : aluResult = forwardOut;  // SELECT = 0 : FORWARD
            3'b001 : aluResult = addOut;      // SELECT = 1 : ADD
            3'b010 : aluResult = andOut;      // SELECT = 2 : AND
            3'b011 : aluResult = orOut;       // SELECT = 3 : OR
        endcase
    end
endmodule

// Define the ADD module for addition operation
module ADD(out, data1, data2,zero);
    input [7:0] data1, data2;  // Input data for addition
    output [7:0] out;  // Output result
    output zero;

    assign #2 out = data1 + data2;  // Perform addition with delay of 2 time units
    assign zero = (out == 8'b00000000); 
    
endmodule

// Define the AND module for bitwise AND operation
module AND(out, data1, data2);
    input [7:0] data1, data2;  // Input data for AND operation
    output [7:0] out;  // Output result
    
    assign #1 out = data1 & data2;  // Perform AND operation with delay of 1 time unit
endmodule

// Define the FORWARD module to pass data1 directly to output
module FORWARD(out, data2);
    input [7:0] data2;  // Input data
    output [7:0] out;  // Output result
    
    assign #1 out = data2;  // Output is the same as input with delay of 1 time unit
endmodule

// Define the OR module for bitwise OR operation
module OR(out, data1, data2);
    input [7:0] data1, data2;  // Input data for OR operation
    output [7:0] out;  // Output result
    
    assign #1 out = data1 | data2;  // Perform OR operation with delay of 1 time unit
endmodule

reg.v
module reg_file(IN, OUT1, OUT2, INADDRESS, OUT1ADDRESS, OUT2ADDRESS, WRITE, CLK, RESET );

    input [7:0] IN;  // Input data
    input [2:0] INADDRESS, OUT1ADDRESS, OUT2ADDRESS;  // Input/output address
    input WRITE, CLK, RESET;  // Control signals

    output  [7:0] OUT1, OUT2;  // Output data

    reg [7:0] register [7:0];  // 8 registers, each 8 bits
    integer i;  // Integer for loop iteration

    // Asynchronously reading with 2 time delay
    assign #2 OUT1 = register[OUT1ADDRESS];  // Assign output 1 based on OUT1ADDRESS
    assign #2 OUT2 = register[OUT2ADDRESS];  // Assign output 2 based on OUT2ADDRESS

    // Synchronously reading and writing with 1 time delay
    always @(posedge CLK) begin  // Triggered on positive clock edge
        if (RESET == 1'b1) begin  // Reset condition
            for (i = 0; i < 8; i = i + 1) begin  // Loop through each register
                register[i] <= 8'b00000000;  // Reset each register to all zeros
            end
        end
        else if (WRITE == 1'b1)  // Write condition
            #1 register[INADDRESS] <= IN;  // Write IN data to the specified address in register array
    end

endmodule

control_unit.v
/*
Group 11 Lab 5 part 4

*/



module control_unit(OPCODE,WRITE_ENABLE,ALUOP,REG2_SIGN_SEL,OP2_SEL,JUMP,BRANCH);

    input [7:0] OPCODE;
    output reg WRITE_ENABLE,REG2_SIGN_SEL,OP2_SEL;    //Used in procedeual block. Hence reg use
    output reg [2:0] ALUOP;
    output reg JUMP,BRANCH;
    

/*  loadi = "00000000"
	  mov 	= "00000001"
	  add 	= "00000010"
	  sub 	= "00000011"
	  and 	= "00000100"
	  or  	= "00000101" 
    jump  = "00000110" 
    beq   = "00000111"  */

/*  SELECT = 000 : FORWARD
    SELECT = 001 : ADD
    SELECT = 010 : AND
    SELECT = 011 : OR             */
    

    always @ (OPCODE)begin
      
      JUMP = 0;
      BRANCH=0;

      case (OPCODE)
        //loadi
        8'b00000000: #1 {WRITE_ENABLE,ALUOP,REG2_SIGN_SEL,OP2_SEL} = 6'b1_000_x_1;   //OP2_SEL       = 0: Reg2 out  , 1: Immidiate value 
                                                                                     //Reg2_Sign_SEL = 0:Positive value 
        //mov
        8'b00000001: #1 {WRITE_ENABLE,ALUOP,REG2_SIGN_SEL,OP2_SEL} = 6'b1_000_0_0;

        //add
        8'b00000010: #1 {WRITE_ENABLE,ALUOP,REG2_SIGN_SEL,OP2_SEL} = 6'b1_001_0_0;

        //sub
        8'b00000011: #1 {WRITE_ENABLE,ALUOP,REG2_SIGN_SEL,OP2_SEL} = 6'b1_001_1_0;

        //and
        8'b00000100: #1 {WRITE_ENABLE,ALUOP,REG2_SIGN_SEL,OP2_SEL} = 6'b1_010_0_0;

        //or
        8'b00000101: #1 {WRITE_ENABLE,ALUOP,REG2_SIGN_SEL,OP2_SEL} = 6'b1_011_0_0;

        //jump
        8'b00000110: #1 {WRITE_ENABLE,ALUOP,REG2_SIGN_SEL,OP2_SEL,JUMP} = 7'b0_xxx_x_x_1;

        //beq
	      8'b00000111: #1 {WRITE_ENABLE,ALUOP,REG2_SIGN_SEL,OP2_SEL,BRANCH} = 7'b0_001_1_0_1;

               
      endcase



    end


endmodule

cpu.v
/*
Group 11 Lab 5 part 4

*/

`include "addition_modules.v"
`include "control_unit.v"
`include "reg.v"
`include "alu.v"

module cpu(PC,INSTRUCTION,CLK,RESET);

    input [31:0] INSTRUCTION;  // Input instruction
    input CLK,RESET;  // Clock and reset signals
    output [31:0] PC;  // Program counter output

    wire [7:0] opcode , immediate,offset;  // Wires for opcode and immediate value
    wire [2:0] readreg1 , readreg2 , writereg , aluop;  // Wires for register and ALU operations
    wire write_enable , reg2_sign_sel , op2_sel;  // Control signals

    // Extract opcode, immediate value, and register operations from the instruction
    assign opcode   = INSTRUCTION[31:24];
    assign immediate = INSTRUCTION[7:0];
    assign readreg1 = INSTRUCTION[10:8];
    assign readreg2 = INSTRUCTION[2:0];
    assign writereg = INSTRUCTION [18:16]; 
    assign offset = INSTRUCTION [23:16];

    wire jump,branch,zero;
    wire [7:0] regout2,regout1;  // Register output signals
    wire [7:0] aluresult;  // ALU result
    wire [7:0] regout2_negative;  // Negative of regout2
    wire [7:0] reg2_mux_out;  // Output of the second mux
    wire [7:0] oprend2;  // Operand 2 for the ALU

    // Instantiate Modules
    control_unit cpu_control(opcode,write_enable,aluop,reg2_sign_sel,op2_sel,jump,branch);    // Instantiate control unit
    
    reg_file cpu_reg(aluresult, regout1, regout2, writereg, readreg1, readreg2, write_enable, CLK, RESET ); // Instantiate register file
    
    twos_compliment cpu_compliment(regout2,regout2_negative);   // Compute two's complement of regout2
    
    mux_2x1 cpu_mux1(regout2,regout2_negative,reg2_sign_sel,reg2_mux_out);  // Select between regout2 and its negative using reg2_sign_sel
    
    mux_2x1 cpu_mux2(reg2_mux_out,immediate,op2_sel,oprend2);   // Select between reg2_mux_out and immediate using op2_sel

    alu cpu_alu(aluresult, aluop, regout1, oprend2,zero);   // Perform ALU operation


    wire [31:0] byteAddress;            //Extend and shifted 32bit address
    wire [31:0] pc_4,next_pc,beq_pc;    //PC+4 , Next PC , Output of (PC+4+byteAddress)
    wire branch_sel;                    //Branch Sel = (zero & branch) 
    wire [31:0] branch_mux_out;         //Output Of Branch Select Mux
    wire [31:0] jumpaddress;            //Jump Address

    //Instantiate Other Modules
    extend cpu_extend(offset,byteAddress);  // Extend offset and leftshift by two for address alling

    pc_adder1 cpu_pcadder1(PC,pc_4);    //PC + 4

    pc_adder2 cpu_pcadder2(pc_4,byteAddress,beq_pc);    //PC+4+byteAddress

    branchSel cpu_branch(branch,zero,branch_sel);   //Combinational AND for Branch Select signal. 

    mux_32 cpu_branch_mux(pc_4,beq_pc,branch_sel,branch_mux_out);   //Mux for slect PC+4 or Branch Address
 
    concatenate cpu_concatenate(pc_4,offset,jumpaddress);   //Get Jump Address by concatenating most significant 4 bits of PC+4 with joffset
    
    mux_32 cpu_jump_mux(branch_mux_out,jumpaddress,jump,next_pc);   //Mux for select Branch_mux_out or JumpAddress 

    pc_unit cpu_pc(CLK,RESET,next_pc,PC);   // Instantiate PC unit

    

endmodule

cpu_tb.v
`include "cpu.v"

/* 
Assembly instruction set  which used in Teestbench
loadi 4 0x05    // r4 = 5
loadi 2 0x09    // r2 = 9
add 6 4 2
sub 7 2 4
and 3 4 2
or 5 4 2

*/

module cpu_tb;

    reg CLK,RESET;
    wire [31:0] PC,INSTRUCTION;
    integer i;

    reg [7:0] instruction_mem[1023:0];  //Array for store Instruction

    initial begin
        $readmemb("instr_mem.mem",instruction_mem);  //Read file wich include binary instruction(32 bit)
    end

    cpu mycpu(PC,INSTRUCTION,CLK,RESET);    //Instantiate Cpu module

    initial begin

        $dumpfile("cpu-wavedata.vcd");      //Wavedata file
        $dumpvars(0,cpu_tb);
        for(i=0;i<8;i++)
			$dumpvars(0,mycpu.cpu_reg.register[i]);     //To observe each registers value

        CLK= 1'b0;      //Initiate CLK=0 and RESET=1
        RESET=1'b1;

        #5
        RESET=1'b0;     //After 5 delay RESET=1

        #100 $finish;
    end

    always #4 CLK=~CLK; //Keep Clock pulse ( T = 8  time unit)

    assign #2 INSTRUCTION = {instruction_mem[PC+3],instruction_mem[PC+2],instruction_mem[PC+1],instruction_mem[PC]};  //Make 32 bit instruction from instuction_mem array


endmodule

cpu-wavedata.vcd
$date
	Sun May 12 09:07:59 2024
$end
$version
	Icarus Verilog
$end
$timescale
	1s
$end
$scope module cpu_tb $end
$var wire 32 ! PC [31:0] $end
$var wire 32 " INSTRUCTION [31:0] $end
$var reg 1 # CLK $end
$var reg 1 $ RESET $end
$var integer 32 % i [31:0] $end
$scope module mycpu $end
$var wire 1 # CLK $end
$var wire 32 & INSTRUCTION [31:0] $end
$var wire 1 $ RESET $end
$var wire 1 ' zero $end
$var wire 3 ( writereg [2:0] $end
$var wire 1 ) write_enable $end
$var wire 8 * regout2_negative [7:0] $end
$var wire 8 + regout2 [7:0] $end
$var wire 8 , regout1 [7:0] $end
$var wire 1 - reg2_sign_sel $end
$var wire 8 . reg2_mux_out [7:0] $end
$var wire 3 / readreg2 [2:0] $end
$var wire 3 0 readreg1 [2:0] $end
$var wire 32 1 pc_4 [31:0] $end
$var wire 8 2 oprend2 [7:0] $end
$var wire 8 3 opcode [7:0] $end
$var wire 1 4 op2_sel $end
$var wire 8 5 offset [7:0] $end
$var wire 32 6 next_pc [31:0] $end
$var wire 32 7 jumpaddress [31:0] $end
$var wire 1 8 jump $end
$var wire 8 9 immediate [7:0] $end
$var wire 32 : byteAddress [31:0] $end
$var wire 1 ; branch_sel $end
$var wire 32 < branch_mux_out [31:0] $end
$var wire 1 = branch $end
$var wire 32 > beq_pc [31:0] $end
$var wire 8 ? aluresult [7:0] $end
$var wire 3 @ aluop [2:0] $end
$var wire 32 A PC [31:0] $end
$scope module cpu_alu $end
$var wire 1 ' zero $end
$var wire 3 B select [2:0] $end
$var wire 8 C orOut [7:0] $end
$var wire 8 D forwardOut [7:0] $end
$var wire 8 E data2 [7:0] $end
$var wire 8 F data1 [7:0] $end
$var wire 8 G andOut [7:0] $end
$var wire 8 H addOut [7:0] $end
$var reg 8 I aluResult [7:0] $end
$scope module add1 $end
$var wire 1 ' zero $end
$var wire 8 J out [7:0] $end
$var wire 8 K data2 [7:0] $end
$var wire 8 L data1 [7:0] $end
$upscope $end
$scope module and1 $end
$var wire 8 M out [7:0] $end
$var wire 8 N data2 [7:0] $end
$var wire 8 O data1 [7:0] $end
$upscope $end
$scope module f $end
$var wire 8 P out [7:0] $end
$var wire 8 Q data2 [7:0] $end
$upscope $end
$scope module or1 $end
$var wire 8 R out [7:0] $end
$var wire 8 S data2 [7:0] $end
$var wire 8 T data1 [7:0] $end
$upscope $end
$upscope $end
$scope module cpu_branch $end
$var wire 1 ; branch_sel $end
$var wire 1 ' zero $end
$var wire 1 = branch $end
$upscope $end
$scope module cpu_branch_mux $end
$var wire 1 ; SELECT $end
$var wire 32 U IN1 [31:0] $end
$var wire 32 V IN0 [31:0] $end
$var reg 32 W OUT [31:0] $end
$upscope $end
$scope module cpu_compliment $end
$var wire 8 X OUT [7:0] $end
$var wire 8 Y IN [7:0] $end
$upscope $end
$scope module cpu_concatenate $end
$var wire 8 Z joffset [7:0] $end
$var wire 32 [ pc_4 [31:0] $end
$var wire 32 \ jumpAddress [31:0] $end
$var wire 28 ] extend_jump [27:0] $end
$upscope $end
$scope module cpu_control $end
$var wire 8 ^ OPCODE [7:0] $end
$var reg 3 _ ALUOP [2:0] $end
$var reg 1 = BRANCH $end
$var reg 1 8 JUMP $end
$var reg 1 4 OP2_SEL $end
$var reg 1 - REG2_SIGN_SEL $end
$var reg 1 ) WRITE_ENABLE $end
$upscope $end
$scope module cpu_extend $end
$var wire 8 ` address [7:0] $end
$var wire 32 a byteAddress [31:0] $end
$upscope $end
$scope module cpu_jump_mux $end
$var wire 32 b IN0 [31:0] $end
$var wire 32 c IN1 [31:0] $end
$var wire 1 8 SELECT $end
$var reg 32 d OUT [31:0] $end
$upscope $end
$scope module cpu_mux1 $end
$var wire 8 e IN1 [7:0] $end
$var wire 1 - SELECT $end
$var wire 8 f IN0 [7:0] $end
$var reg 8 g OUT [7:0] $end
$upscope $end
$scope module cpu_mux2 $end
$var wire 8 h IN0 [7:0] $end
$var wire 8 i IN1 [7:0] $end
$var wire 1 4 SELECT $end
$var reg 8 j OUT [7:0] $end
$upscope $end
$scope module cpu_pc $end
$var wire 1 # CLK $end
$var wire 32 k NEXT_PC [31:0] $end
$var wire 1 $ RESET $end
$var reg 32 l PC [31:0] $end
$upscope $end
$scope module cpu_pcadder1 $end
$var wire 32 m CURRENT_PC [31:0] $end
$var wire 32 n PC_4 [31:0] $end
$upscope $end
$scope module cpu_pcadder2 $end
$var wire 32 o offset [31:0] $end
$var wire 32 p pc_4 [31:0] $end
$var wire 32 q offset_pc [31:0] $end
$upscope $end
$scope module cpu_reg $end
$var wire 1 # CLK $end
$var wire 8 r IN [7:0] $end
$var wire 3 s INADDRESS [2:0] $end
$var wire 8 t OUT1 [7:0] $end
$var wire 3 u OUT1ADDRESS [2:0] $end
$var wire 8 v OUT2 [7:0] $end
$var wire 3 w OUT2ADDRESS [2:0] $end
$var wire 1 $ RESET $end
$var wire 1 ) WRITE $end
$var integer 32 x i [31:0] $end
$upscope $end
$upscope $end
$upscope $end
$scope module cpu_tb $end
$scope module mycpu $end
$scope module cpu_reg $end
$var reg 8 y \register[0] [7:0] $end
$upscope $end
$upscope $end
$upscope $end
$scope module cpu_tb $end
$scope module mycpu $end
$scope module cpu_reg $end
$var reg 8 z \register[1] [7:0] $end
$upscope $end
$upscope $end
$upscope $end
$scope module cpu_tb $end
$scope module mycpu $end
$scope module cpu_reg $end
$var reg 8 { \register[2] [7:0] $end
$upscope $end
$upscope $end
$upscope $end
$scope module cpu_tb $end
$scope module mycpu $end
$scope module cpu_reg $end
$var reg 8 | \register[3] [7:0] $end
$upscope $end
$upscope $end
$upscope $end
$scope module cpu_tb $end
$scope module mycpu $end
$scope module cpu_reg $end
$var reg 8 } \register[4] [7:0] $end
$upscope $end
$upscope $end
$upscope $end
$scope module cpu_tb $end
$scope module mycpu $end
$scope module cpu_reg $end
$var reg 8 ~ \register[5] [7:0] $end
$upscope $end
$upscope $end
$upscope $end
$scope module cpu_tb $end
$scope module mycpu $end
$scope module cpu_reg $end
$var reg 8 !" \register[6] [7:0] $end
$upscope $end
$upscope $end
$upscope $end
$scope module cpu_tb $end
$scope module mycpu $end
$scope module cpu_reg $end
$var reg 8 "" \register[7] [7:0] $end
$upscope $end
$upscope $end
$upscope $end
$enddefinitions $end
$comment Show the parameter values. $end
$dumpall
$end
#0
$dumpvars
bx ""
bx !"
bx ~
bx }
bx |
bx {
bx z
bx y
bx x
bx w
bx v
bx u
bx t
bx s
bx r
bx q
bx p
bx00 o
bx n
bx m
bx l
bx00 k
bx j
bx i
bx h
bx g
bx f
bx e
bx00 d
bx00 c
bx b
bx00 a
bx `
bx _
bx ^
bx00 ]
bx00 \
bx [
bx Z
bx Y
bx X
bx W
bx V
bx U
bx T
bx S
bx R
bx Q
bx P
bx O
bx N
bx M
bx L
bx K
bx J
bx I
bx H
bx G
bx F
bx E
bx D
bx C
bx B
bx A
bx @
bx ?
bx >
x=
bx <
x;
bx00 :
bx 9
x8
bx00 7
bx00 6
bx 5
x4
bx 3
bx 2
bx 1
bx 0
bx /
bx .
x-
bx ,
bx +
bx *
x)
bx (
x'
bx &
b1000 %
1$
0#
bx "
bx !
$end
#4
b0 ""
b0 !"
b0 ~
b0 }
b0 |
b0 {
b0 z
b0 y
b1000 x
1#
#5
b0 !
b0 A
b0 l
b0 m
0$
#6
b0xxxxxxxxxxxxxxxxxxxxxxxxxx00 6
b0xxxxxxxxxxxxxxxxxxxxxxxxxx00 d
b0xxxxxxxxxxxxxxxxxxxxxxxxxx00 k
b0xxxxxxxxxxxxxxxxxxxxxxxxxx00 7
b0xxxxxxxxxxxxxxxxxxxxxxxxxx00 \
b0xxxxxxxxxxxxxxxxxxxxxxxxxx00 c
b100 1
b100 V
b100 [
b100 n
b100 p
#7
b100 <
b100 W
b100 b
0;
b100 6
b100 d
b100 k
0=
08
b101 2
b101 E
b101 K
b101 N
b101 Q
b101 S
b101 j
b10000 7
b10000 \
b10000 c
b10000 ]
b10000 :
b10000 a
b10000 o
b0 3
b0 ^
b101 9
b101 i
b0 0
b0 u
b101 /
b101 w
b100 (
b100 s
b100 5
b100 Z
b100 `
b1000000000000000101 "
b1000000000000000101 &
#8
b101 ?
b101 I
b101 r
bx1x1 C
bx1x1 R
b0x0x G
b0x0x M
b10100 >
b10100 U
b10100 q
1)
b0 @
b0 B
b0 _
14
b101 D
b101 P
0#
#9
b0 ,
b0 F
b0 L
b0 O
b0 T
b0 t
b0 +
b0 Y
b0 f
b0 v
#10
b0 .
b0 g
b0 h
b101 C
b101 R
b0 G
b0 M
b0 *
b0 X
b0 e
#11
0'
b101 H
b101 J
#12
1#
#13
b101 }
b100 !
b100 A
b100 l
b100 m
#14
b1000 6
b1000 d
b1000 k
b1000 <
b1000 W
b1000 b
b1000 1
b1000 V
b1000 [
b1000 n
b1000 p
#15
b1000 7
b1000 \
b1000 c
b1000 ]
b1000 :
b1000 a
b1000 o
b10 (
b10 s
b10 5
b10 Z
b10 `
b11000 >
b11000 U
b11000 q
b100000000000000101 "
b100000000000000101 &
#16
b10000 >
b10000 U
b10000 q
0#
#20
1#
#21
b101 {
b1000 !
b1000 A
b1000 l
b1000 m
#22
b1100 6
b1100 d
b1100 k
b1100 <
b1100 W
b1100 b
b1100 1
b1100 V
b1100 [
b1100 n
b1100 p
#23
b0 2
b0 E
b0 K
b0 N
b0 Q
b0 S
b0 j
b11100 7
b11100 \
b11100 c
b11100 ]
b11100 :
b11100 a
b11100 o
b110 3
b110 ^
b0 9
b0 i
b0 /
b0 w
b111 (
b111 s
b111 5
b111 Z
b111 `
b10100 >
b10100 U
b10100 q
b110000001110000000000000000 "
b110000001110000000000000000 &
#24
b11100 6
b11100 d
b11100 k
b0 C
b0 R
0)
bx @
bx B
bx _
x4
18
b0 D
b0 P
b101000 >
b101000 U
b101000 q
0#
#25
1'
b0 H
b0 J
#28
1#
#29
b11100 !
b11100 A
b11100 l
b11100 m
#30
b100000 <
b100000 W
b100000 b
b100000 1
b100000 V
b100000 [
b100000 n
b100000 p
#31
b100000 6
b100000 d
b100000 k
08
b100 2
b100 E
b100 K
b100 N
b100 Q
b100 S
b100 j
b1111111111111111111111101100 7
b1111111111111111111111101100 \
b1111111111111111111111101100 c
b1111111111111111111111101100 ]
b11111111111111111111111111101100 :
b11111111111111111111111111101100 a
b11111111111111111111111111101100 o
b111 3
b111 ^
b100 9
b100 i
b10 0
b10 u
b100 /
b100 w
b11 (
b11 s
b11111011 5
b11111011 Z
b11111011 `
b111100 >
b111100 U
b111100 q
b111111110110000001000000100 "
b111111110110000001000000100 &
#32
b1100 6
b1100 d
b1100 k
b1100 <
b1100 W
b1100 b
b0 2
b0 E
b0 K
b0 N
b0 Q
b0 S
b0 j
1;
b0 ?
b0 I
b0 r
b100 C
b100 R
b1 @
b1 B
b1 _
1-
04
1=
b100 D
b100 P
b1100 >
b1100 U
b1100 q
0#
#33
b0 C
b0 R
b0 D
b0 P
b101 ,
b101 F
b101 L
b101 O
b101 T
b101 t
b101 +
b101 Y
b101 f
b101 v
#34
b11111011 2
b11111011 E
b11111011 K
b11111011 N
b11111011 Q
b11111011 S
b11111011 j
b11111011 .
b11111011 g
b11111011 h
b101 C
b101 R
b11111011 *
b11111011 X
b11111011 e
#35
b11111111 C
b11111111 R
b1 G
b1 M
b11111011 D
b11111011 P
#36
1#
#37
b1100 !
b1100 A
b1100 l
b1100 m
#38
b10000 1
b10000 V
b10000 [
b10000 n
b10000 p
#39
0;
b10000 6
b10000 d
b10000 k
0=
b10000 7
b10000 \
b10000 c
b10000 ]
b10000 :
b10000 a
b10000 o
b10000 <
b10000 W
b10000 b
b10 3
b10 ^
b10 9
b10 i
b100 0
b100 u
b10 /
b10 w
b100 (
b100 s
b100 5
b100 Z
b100 `
b11111111111111111111111111111100 >
b11111111111111111111111111111100 U
b11111111111111111111111111111100 q
b10000001000000010000000010 "
b10000001000000010000000010 &
#40
b101 2
b101 E
b101 K
b101 N
b101 Q
b101 S
b101 j
b101 .
b101 g
b101 h
1)
0-
b100000 >
b100000 U
b100000 q
0#
#41
b101 C
b101 R
b101 G
b101 M
b101 D
b101 P
#42
b1010 ?
b1010 I
b1010 r
0'
b1010 H
b1010 J
#44
1#
#45
b1010 }
b10000 !
b10000 A
b10000 l
b10000 m
#46
b10100 6
b10100 d
b10100 k
b10100 <
b10100 W
b10100 b
b10100 1
b10100 V
b10100 [
b10100 n
b10100 p
#47
b11100 7
b11100 \
b11100 c
b11100 ]
b11100 :
b11100 a
b11100 o
b11 3
b11 ^
b100 9
b100 i
b10 0
b10 u
b100 /
b100 w
b111 (
b111 s
b111 5
b111 Z
b111 `
b100100 >
b100100 U
b100100 q
b1010 ,
b1010 F
b1010 L
b1010 O
b1010 T
b1010 t
b11000001110000001000000100 "
b11000001110000001000000100 &
#48
b11111011 2
b11111011 E
b11111011 K
b11111011 N
b11111011 Q
b11111011 S
b11111011 j
b11111011 .
b11111011 g
b11111011 h
1-
b110000 >
b110000 U
b110000 q
b1111 C
b1111 R
b0 G
b0 M
0#
#49
b11111011 C
b11111011 R
b1010 G
b1010 M
b11111011 D
b11111011 P
b101 ,
b101 F
b101 L
b101 O
b101 T
b101 t
b1010 +
b1010 Y
b1010 f
b1010 v
#50
b11110110 2
b11110110 E
b11110110 K
b11110110 N
b11110110 Q
b11110110 S
b11110110 j
b11110110 .
b11110110 g
b11110110 h
b11111111 C
b11111111 R
b1 G
b1 M
b11110110 *
b11110110 X
b11110110 e
#51
b11110111 C
b11110111 R
b100 G
b100 M
b11110110 D
b11110110 P
#52
b11111011 ?
b11111011 I
b11111011 r
b11111011 H
b11111011 J
1#
#53
b11111011 ""
b10100 !
b10100 A
b10100 l
b10100 m
#54
b11000 6
b11000 d
b11000 k
b11000 <
b11000 W
b11000 b
b11000 1
b11000 V
b11000 [
b11000 n
b11000 p
#55
b1100 7
b1100 \
b1100 c
b1100 ]
b1100 :
b1100 a
b1100 o
b100 3
b100 ^
b10 9
b10 i
b100 0
b100 u
b10 /
b10 w
b11 (
b11 s
b11 5
b11 Z
b11 `
b110100 >
b110100 U
b110100 q
b100000000110000010000000010 "
b100000000110000010000000010 &
#56
b1010 2
b1010 E
b1010 K
b1010 N
b1010 Q
b1010 S
b1010 j
b100 ?
b100 I
b100 r
b1010 .
b1010 g
b1010 h
b10 @
b10 B
b10 _
0-
b100100 >
b100100 U
b100100 q
0#
#57
b101 2
b101 E
b101 K
b101 N
b101 Q
b101 S
b101 j
b0 ?
b0 I
b0 r
b101 .
b101 g
b101 h
b1111 C
b1111 R
b0 G
b0 M
b1010 D
b1010 P
b1010 ,
b1010 F
b1010 L
b1010 O
b1010 T
b1010 t
b101 +
b101 Y
b101 f
b101 v
#58
b101 D
b101 P
b11111011 *
b11111011 X
b11111011 e
#59
b1111 H
b1111 J
#60
1#
#61
b0 |
b11000 !
b11000 A
b11000 l
b11000 m
#62
b11100 6
b11100 d
b11100 k
b11100 <
b11100 W
b11100 b
b11100 1
b11100 V
b11100 [
b11100 n
b11100 p
#63
b10100 7
b10100 \
b10100 c
b10100 ]
b10100 :
b10100 a
b10100 o
b101 3
b101 ^
b101 (
b101 s
b101 5
b101 Z
b101 `
b101000 >
b101000 U
b101000 q
b101000001010000010000000010 "
b101000001010000010000000010 &
#64
b1111 ?
b1111 I
b1111 r
b11 @
b11 B
b11 _
b110000 >
b110000 U
b110000 q
0#
#68
1#
#69
b1111 ~
b11100 !
b11100 A
b11100 l
b11100 m
#70
b100000 6
b100000 d
b100000 k
b100000 <
b100000 W
b100000 b
b100000 1
b100000 V
b100000 [
b100000 n
b100000 p
#71
b1111111111111111111111101100 7
b1111111111111111111111101100 \
b1111111111111111111111101100 c
b1111111111111111111111101100 ]
b11111111111111111111111111101100 :
b11111111111111111111111111101100 a
b11111111111111111111111111101100 o
b111 3
b111 ^
b100 9
b100 i
b10 0
b10 u
b100 /
b100 w
b11 (
b11 s
b11111011 5
b11111011 Z
b11111011 `
b110100 >
b110100 U
b110100 q
b111111110110000001000000100 "
b111111110110000001000000100 &
#72
b11111011 2
b11111011 E
b11111011 K
b11111011 N
b11111011 Q
b11111011 S
b11111011 j
b11111011 .
b11111011 g
b11111011 h
0)
b1 @
b1 B
b1 _
1-
1=
b1100 >
b1100 U
b1100 q
0#
#73
b11111011 C
b11111011 R
b1010 G
b1010 M
b11111011 D
b11111011 P
b101 ,
b101 F
b101 L
b101 O
b101 T
b101 t
b1010 +
b1010 Y
b1010 f
b1010 v
#74
b11110110 2
b11110110 E
b11110110 K
b11110110 N
b11110110 Q
b11110110 S
b11110110 j
b11110110 .
b11110110 g
b11110110 h
b11111111 C
b11111111 R
b1 G
b1 M
b11110110 *
b11110110 X
b11110110 e
#75
b11110111 C
b11110111 R
b100 G
b100 M
b11110110 D
b11110110 P
#76
b11111011 ?
b11111011 I
b11111011 r
b11111011 H
b11111011 J
1#
#77
b100000 !
b100000 A
b100000 l
b100000 m
#78
b100100 6
b100100 d
b100100 k
b100100 <
b100100 W
b100100 b
b100100 1
b100100 V
b100100 [
b100100 n
b100100 p
#79
0=
b0xxxxxxxxxxxxxxxxxxxxxxxxxx00 7
b0xxxxxxxxxxxxxxxxxxxxxxxxxx00 \
b0xxxxxxxxxxxxxxxxxxxxxxxxxx00 c
bx00 ]
bx00 :
bx00 a
bx00 o
bx 3
bx ^
bx 9
bx i
bx 0
bx u
bx /
bx w
bx (
bx s
bx 5
bx Z
bx `
b10000 >
b10000 U
b10000 q
bx "
bx &
#80
bx >
bx U
bx q
0#
#81
bx ,
bx F
bx L
bx O
bx T
bx t
bx +
bx Y
bx f
bx v
#82
bx 2
bx E
bx K
bx N
bx Q
bx S
bx j
bx .
bx g
bx h
b1111x11x C
b1111x11x R
bx0xx0 G
bx0xx0 M
bx *
bx X
bx e
